{
  "project_info": {
    "project_number": "445324070896",
    "project_id": "oraxtech-mynotes",
    "storage_bucket": "oraxtech-mynotes.appspot.com"
  },
  "client": [
    {
      "client_info": {
        "mobilesdk_app_id": "1:445324070896:android:a95993d422a1fe5aa09735",
        "android_client_info": {
          "package_name": "com.oraxtech.mynotes"
        }
      },
      "oauth_client": [
        {
          "client_id": "445324070896-offsfj8c97g6sjk5naffpl15eloma31t.apps.googleusercontent.com",
          "client_type": 3
        }
      ],
      "api_key": [
        {
          "current_key": "AIzaSyCEHS33spDsPb5ecoX8xAJtsiYv944dAco"
        }
      ],
      "services": {
        "appinvite_service": {
          "other_platform_oauth_client": [
            {
              "client_id": "445324070896-offsfj8c97g6sjk5naffpl15eloma31t.apps.googleusercontent.com",
              "client_type": 3
            }
          ]
        }
      }
    }
  ],
  "configuration_version": "1"
}